pycy
setup.py
PyCommunity.egg-info/PKG-INFO
PyCommunity.egg-info/SOURCES.txt
PyCommunity.egg-info/dependency_links.txt
PyCommunity.egg-info/requires.txt
PyCommunity.egg-info/top_level.txt
pycommunity/__init__.py
pycommunity/configuration.py
pycommunity/generator.py
pycommunity/glossary.py
pycommunity/index.py
pycommunity/package.py
pycommunity/recipe.py
pycommunity/resttask.py
pycommunity/sitebuilder.py
pycommunity/tasks.py
pycommunity/test_docs.py
pycommunity/tutorial.py
pycommunity/utils.py
