Metadata-Version: 1.0
Name: PyCommunity
Version: 0.1a
Summary: Automatic website builder, using doctests and other reST files.
Home-page: http://programmation-python.org/pycommunity
Author: Tarek Ziade
Author-email: tarek@ziade.org
License: http://www.gnu.org/copyleft/gpl.html
Platform: any
Classifier: Development Status :: 3 - Alpha
Classifier: Intended Audience :: Developers
Classifier: License :: OSI Approved :: GNU General Public License (GPL)
Classifier: Programming Language :: Python
Classifier: Topic :: Software Development
Classifier: Operating System :: Microsoft :: Windows
Classifier: Operating System :: Unix
